[{"filter_id":1,"clients":[{"id":1,"number":"(098)1538845","name":" Юрий","car":"BMW X6 2020","interested":"No","messanger":"None"},{"id":2,"number":"(099)0350490","name":" Євген Афанасьєв","car":"Volkswagen Touareg 2011","interested":"No","messanger":"None"},{"id":3,"number":"(093)9665357","name":" Yuriy","car":"Volkswagen Touareg 2021","interested":"No","messanger":"None"},{"id":4,"number":"(063)0506050","name":" Александр Олегович Карпенко","car":"BMW X5 2014","interested":"No","messanger":"None"},{"id":5,"number":"(095)5888202","name":" Сергій","car":"Volkswagen Passat Alltrack 2019","interested":"No","messanger":"None"},{"id":6,"number":"(063)1190622","name":" Алексей","car":"BMW X5 2017","interested":"No","messanger":"None"},{"id":7,"number":"(063)4563075","name":"Ім’я не вказане","car":"Renault Megane 2007","interested":"No","messanger":"None"},{"id":8,"number":"(063)1683038","name":" Даниїл Вячеславович Христюк","car":"Renault Megane 2012","interested":"No","messanger":"None"},{"id":9,"number":"(096)5598682","name":" Андрій Васильович","car":"Renault Megane 2012","interested":"No","messanger":"None"},{"id":10,"number":"(097)7235775","name":" Віталій Олександрович","car":"Audi Q7 2010","interested":"No","messanger":"None"},{"id":11,"number":"(050)0344004","name":" Владислав","car":"Audi Q7 2016","interested":"No","messanger":"None"},{"id":12,"number":"(063)2591205","name":" Олексій","car":"Audi Q7 2008","interested":"No","messanger":"None"},{"id":13,"number":"(073)1023806","name":" Дмитрий","car":"Mercedes-Benz C-Class 2019","interested":"No","messanger":"None"}],"status":"sending"}]